subtitld/__init__.py
subtitld/__main__.py
subtitld/resources_rc.py
subtitld/autosub/__init__.py
subtitld/autosub/constants.py
subtitld/autosub/formatters.py
subtitld/graphics/Ubuntu-B.ttf
subtitld/graphics/Ubuntu-BI.ttf
subtitld/graphics/Ubuntu-C.ttf
subtitld/graphics/Ubuntu-L.ttf
subtitld/graphics/Ubuntu-LI.ttf
subtitld/graphics/Ubuntu-M.ttf
subtitld/graphics/Ubuntu-MI.ttf
subtitld/graphics/Ubuntu-R.ttf
subtitld/graphics/Ubuntu-RI.ttf
subtitld/graphics/Ubuntu-Th.ttf
subtitld/graphics/UbuntuMono-B.ttf
subtitld/graphics/UbuntuMono-BI.ttf
subtitld/graphics/UbuntuMono-R.ttf
subtitld/graphics/UbuntuMono-RI.ttf
subtitld/graphics/add_and_play.svg
subtitld/graphics/add_from_last.svg
subtitld/graphics/add_subtitle_icon.svg
subtitld/graphics/alert_icon.svg
subtitld/graphics/background_watermark.svg
subtitld/graphics/button_dark_disabled.svg
subtitld/graphics/button_dark_hover.svg
subtitld/graphics/button_dark_normal.svg
subtitld/graphics/button_dark_pressed.svg
subtitld/graphics/button_disabled.svg
subtitld/graphics/button_green_disabled.svg
subtitld/graphics/button_green_hover.svg
subtitld/graphics/button_green_normal.svg
subtitld/graphics/button_green_pressed.svg
subtitld/graphics/button_hover.svg
subtitld/graphics/button_normal.svg
subtitld/graphics/button_pressed.svg
subtitld/graphics/button_red_disabled.svg
subtitld/graphics/button_red_hover.svg
subtitld/graphics/button_red_normal.svg
subtitld/graphics/button_red_pressed.svg
subtitld/graphics/character_count_icon.svg
subtitld/graphics/cps_icon.svg
subtitld/graphics/find_back.svg
subtitld/graphics/find_casesensitive.svg
subtitld/graphics/find_next.svg
subtitld/graphics/gap_add_icon.svg
subtitld/graphics/gap_remove_icon.svg
subtitld/graphics/global_config_subtitles_background.svg
subtitld/graphics/global_config_video_background.svg
subtitld/graphics/grid_frames_icon.svg
subtitld/graphics/grid_scenes_icon.svg
subtitld/graphics/grid_seconds_icon.svg
subtitld/graphics/installer_bar.bmp
subtitld-23.2.0.0.dist-info/LICENSE
subtitld-23.2.0.0.dist-info/METADATA
subtitld-23.2.0.0.dist-info/WHEEL
subtitld-23.2.0.0.dist-info/entry_points.txt
subtitld-23.2.0.0.dist-info/top_level.txt
subtitld-23.2.0.0.dist-info/RECORD
