Metadata-Version: 2.1
Name: subtitld
Version: 23.2.0.0
Summary: Subtitld
Home-page: https://subtitld.org
Author: Jonatã Bolzan Loss
Author-email: subtitld@subtitld.org
License: GPL3
Keywords: subtitld
Classifier: Development Status :: 5 - Production/Stable
Classifier: Environment :: X11 Applications :: Qt
Classifier: Intended Audience :: End Users/Desktop
Classifier: License :: OSI Approved :: GNU General Public License v3 or later (GPLv3+)
Classifier: Natural Language :: English
Classifier: Operating System :: POSIX
Classifier: Topic :: Multimedia
Classifier: Programming Language :: Python :: 3 :: Only
License-File: LICENSE
Requires-Dist: PySide6 (==6.4.0)
Requires-Dist: pyopengl
Requires-Dist: python-mpv (==0.5.2)
Requires-Dist: ffms2
Requires-Dist: numpy
Requires-Dist: cffi
Requires-Dist: requests
Requires-Dist: pycaption
Requires-Dist: pysubs2
Requires-Dist: clean-text[gpl]
Requires-Dist: html5lib (==1.0b8)
Requires-Dist: translate
Requires-Dist: SpeechRecognition
Requires-Dist: beautifulsoup4 (<4.10,>=4.8.1)
Requires-Dist: python-docx
Requires-Dist: chardet
Requires-Dist: google-api-python-client
Requires-Dist: pysrt
Requires-Dist: certifi
Requires-Dist: python-i18n
Requires-Dist: google-cloud-core
